pyops/__init__.py
pyops/base.py
pyops/decorator.py
pyops/libs.py
pyops/main.py
pyops/py_request.py
pyops/pytestplus.py
pyops/ext/__init__.py
pyops/ext/utils/__init__.py
py_ops-0.1.4.dist-info/LICENSE
py_ops-0.1.4.dist-info/METADATA
py_ops-0.1.4.dist-info/WHEEL
py_ops-0.1.4.dist-info/entry_points.txt
py_ops-0.1.4.dist-info/top_level.txt
py_ops-0.1.4.dist-info/RECORD
