Metadata-Version: 2.1
Name: py-ops
Version: 0.1.4
Summary: a python base auto testing framework that programming oriented with Structured Language.
Home-page: https://github.com/five3/pyops.git
Author: Xiaowu Chen
Author-email: five3@163.com
License: MIT V3
Keywords: python unit testing,auto testing,keyword base framework,BDD testing
Platform: any
Classifier: Programming Language :: Python :: 3
Classifier: License :: OSI Approved :: MIT License
Classifier: Operating System :: OS Independent
Classifier: Framework :: Pytest
Requires-Dist: pytest (>=5.0.1)
Requires-Dist: pytestreport (>=0.1.9.3)
